{"nodes": [{"id": "index_html_entry_point", "label": "HTML Entry Point", "file_type": "code", "source_file": "index.html", "source_location": null, "source_url": null, "captured_at": null, "author": "Lovable", "contributor": null}, {"id": "index_html_caship_app", "label": "Caship Application", "file_type": "rationale", "source_file": "index.html", "source_location": null, "source_url": null, "captured_at": null, "author": "Lovable", "contributor": null}, {"id": "index_html_finance_flow", "label": "Finance Flow Personal Finance Tracker", "file_type": "rationale", "source_file": "index.html", "source_location": null, "source_url": null, "captured_at": null, "author": "Lovable", "contributor": null}, {"id": "index_html_google_fonts", "label": "Google Fonts (Instrument Sans)", "file_type": "rationale", "source_file": "index.html", "source_location": null, "source_url": "https://fonts.googleapis.com", "captured_at": null, "author": null, "contributor": null}], "edges": [{"source": "index_html_entry_point", "target": "src_main_tsx", "relation": "references", "confidence": "EXTRACTED", "confidence_score": 1.0, "source_file": "index.html", "source_location": "line 31", "weight": 1.0}, {"source": "index_html_entry_point", "target": "index_html_caship_app", "relation": "references", "confidence": "EXTRACTED", "confidence_score": 1.0, "source_file": "index.html", "source_location": "line 7", "weight": 1.0}, {"source": "index_html_entry_point", "target": "index_html_finance_flow", "relation": "references", "confidence": "EXTRACTED", "confidence_score": 1.0, "source_file": "index.html", "source_location": "line 8", "weight": 1.0}, {"source": "index_html_entry_point", "target": "index_html_google_fonts", "relation": "references", "confidence": "EXTRACTED", "confidence_score": 1.0, "source_file": "index.html", "source_location": "line 20", "weight": 1.0}, {"source": "index_html_caship_app", "target": "index_html_finance_flow", "relation": "semantically_similar_to", "confidence": "INFERRED", "confidence_score": 0.85, "source_file": "index.html", "source_location": null, "weight": 0.85}], "hyperedges": [{"id": "caship_pwa_entry_pattern", "label": "Caship PWA Entry Point Pattern", "nodes": ["index_html_entry_point", "src_main_tsx", "index_html_caship_app"], "relation": "implement", "confidence": "INFERRED", "confidence_score": 0.85, "source_file": "index.html"}]}